gaussianprimes.cpython-39-darwin.so
gaussianprimes-1.0.1.dist-info/LICENSE.md
gaussianprimes-1.0.1.dist-info/METADATA
gaussianprimes-1.0.1.dist-info/WHEEL
gaussianprimes-1.0.1.dist-info/top_level.txt
gaussianprimes-1.0.1.dist-info/RECORD
