Metadata-Version: 2.1
Name: gaussianprimes
Version: 1.0.1
Summary: Generate Gaussian primes.
Home-page: https://github.com/zebengberg/gaussian-integer-sieve
Author: Zeb Engberg
Author-email: zebengberg@gmail.com
License: MIT
Platform: UNKNOWN
Classifier: License :: OSI Approved :: MIT License
Classifier: Programming Language :: Python :: 3
Classifier: Topic :: Scientific/Engineering :: Mathematics
Classifier: Topic :: Scientific/Engineering :: Visualization
Requires-Python: >=3.7
